ccip_terminal/__init__.py
ccip_terminal/account_state.py
ccip_terminal/accounts.py
ccip_terminal/apis.py
ccip_terminal/ccip.py
ccip_terminal/config.py
ccip_terminal/core.py
ccip_terminal/decorators.py
ccip_terminal/env.py
ccip_terminal/gas_estimation_script.py
ccip_terminal/logger.py
ccip_terminal/metadata.py
ccip_terminal/network.py
ccip_terminal/notifications.py
ccip_terminal/token_utils.py
ccip_terminal/utils.py
ccip_terminal/wallet.py
ccip_terminal/web3_utils.py
ccip_terminal/abi/ccip_router_abi.json
ccip_terminal/abi/erc20_abi.json
ccip_terminal/abi/offramp_abi.json
ccip_terminal-0.1.3.dist-info/licenses/LICENSE.txt
ccip_terminal-0.1.3.dist-info/METADATA
ccip_terminal-0.1.3.dist-info/WHEEL
ccip_terminal-0.1.3.dist-info/top_level.txt
ccip_terminal-0.1.3.dist-info/RECORD
