Metadata-Version: 2.4
Name: ccip-terminal
Version: 0.1.3
Summary: Simple Cross-Chain Token Transfers Powered by CCIP
License: MIT
Requires-Python: <4.0,>=3.7
License-File: LICENSE.txt
Provides-Extra: scheduler
Requires-Dist: apscheduler; extra == "scheduler"
Requires-Dist: flask; extra == "scheduler"
Provides-Extra: all
Requires-Dist: flask; extra == "all"
Requires-Dist: apscheduler; extra == "all"
Provides-Extra: dev
Requires-Dist: build; extra == "dev"
Requires-Dist: twine; extra == "dev"
Dynamic: license-file
